strategyenhancement/__init__.py
strategyenhancement/add.py
strategyenhancement/subtract.py
strategyenhancement/extras/__init__.py
strategyenhancement/extras/divide.py
strategyenhancement/extras/multiply.py
strategyenhancement-0.0.1.dist-info/LICENSE
strategyenhancement-0.0.1.dist-info/METADATA
strategyenhancement-0.0.1.dist-info/WHEEL
strategyenhancement-0.0.1.dist-info/top_level.txt
strategyenhancement-0.0.1.dist-info/RECORD
